Workbook

Sheet Assumptions
A1: AeroDesk — Key Assumptions
B2: Year 0 (Pre-Rev) | C2: Year 1 | D2: Year 2 | E2: Year 3 | F2: Year 4 | G2: Year 5 | H2: Notes / Source
A3: MARKET ASSUMPTIONS
A4: Global Used Aircraft Market (USD B) | C4: 40.07 | D4: 42.86 | E4: 45.85 | F4: 49.05 | G4: 52.47 | H4: MRFR 2025 base, 6.97% CAGR
A5: Market CAGR | C5: 0.0697 | D5: 0.0697 | E5: 0.0697 | F5: 0.0697 | G5: 0.0697
A6: Brazil Executive Aircraft Fleet | C6: 10060 | D6: 10301 | E6: 10549 | F6: 10803 | G6: 11063 | H6: ANAC base 9,824 (2023) + 2.4% YoY
A7: Brazil Fleet Growth Rate | C7: 0.024 | D7: 0.024 | E7: 0.024 | F7: 0.024 | G7: 0.024
A8: Addressable Market - Online Aircraft Mktplace (USD M) | C8: 800 | D8: 920 | E8: 1058 | F8: 1217 | G8: 1400 | H8: ~2% of total market = online marketplace TAM
A10: AERODESK MARKET SHARE
A11: AeroDesk Market Share (of online TAM) | B11: 0 | C11: 0.0003 | D11: 0.0014 | E11: 0.0038 | F11: 0.0075 | G11: 0.013
A13: PLATFORM KPIs
A14: Active Dealer Subscribers | B14: 0 | C14: 40 | D14: 150 | E14: 380 | F14: 650 | G14: 1000
A15: Total Active Listings | B15: 0 | C15: 600 | D15: 2200 | E15: 5500 | F15: 10000 | G15: 18000
A16: Monthly Unique Visitors | B16: 0 | C16: 25000 | D16: 120000 | E16: 400000 | F16: 800000 | G16: 1500000
A17: Avg Listing Value (USD) | C17: 850000 | D17: 900000 | E17: 950000 | F17: 1000000 | G17: 1050000 | H17: Blended avg across all aircraft types
A18: Transactions Facilitated | B18: 0 | C18: 15 | D18: 80 | E18: 250 | F18: 550 | G18: 1100 | H18: Closed via platform escrow/financing
A20: REVENUE ASSUMPTIONS
A21: Avg Dealer Subscription ($/mo) | C21: 180 | D21: 220 | E21: 260 | F21: 300 | G21: 340 | H21: Blended Basic/Premium/Enterprise
A22: Featured Listing Fee (avg $/listing) | C22: 350 | D22: 400 | E22: 450 | F22: 500 | G22: 550
A23: Featured Listings Sold / Year | C23: 120 | D23: 450 | E23: 1100 | F23: 2000 | G23: 3500
A24: Individual Listing Fee (avg $) | C24: 80 | D24: 90 | E24: 100 | F24: 110 | G24: 120
A25: Individual Listings Sold / Year | C25: 200 | D25: 800 | E25: 2000 | F25: 4000 | G25: 7000
A26: Transaction Commission Rate | C26: 0.005 | D26: 0.008 | E26: 0.01 | F26: 0.012 | G26: 0.015 | H26: Blended: escrow + financing referral
A27: Insurance Referral (per policy) | C27: 500 | D27: 600 | E27: 700 | F27: 750 | G27: 800
A28: Insurance Policies Referred | B28: 0 | C28: 10 | D28: 50 | E28: 180 | F28: 400 | G28: 800
A29: Pre-Purchase Inspection Referral ($) | C29: 800 | D29: 900 | E29: 1000 | F29: 1000 | G29: 1000
A30: PPI Referrals / Year | B30: 0 | C30: 10 | D30: 60 | E30: 200 | F30: 450 | G30: 900
A31: Legal/Contract Support Referral ($) | C31: 400 | D31: 500 | E31: 600 | F31: 650 | G31: 700
A32: Legal Referrals / Year | B32: 0 | C32: 8 | D32: 45 | E32: 150 | F32: 350 | G32: 700
A33: Data & Analytics Subscribers | B33: 0 | C33: 10 | D33: 40 | E33: 100 | F33: 200 | G33: 350
A34: Data Subscription Avg ($/mo) | C34: 250 | D34: 300 | E34: 350 | F34: 400 | G34: 450
A36: COST ASSUMPTIONS
A37: Headcount | B37: 2 | C37: 8 | D37: 14 | E37: 22 | F37: 32 | G37: 45 | H37: See SG&A detail
A38: Avg Salary + Benefits ($/yr) | C38: 60000 | D38: 65000 | E38: 70000 | F38: 75000 | G38: 80000 | H38: Brazil-weighted, includes benefits
A39: Cloud Infra ($/mo) | B39: 500 | C39: 2000 | D39: 4500 | E39: 8000 | F39: 14000 | G39: 22000 | H39: AWS/Vercel/CDN
A40: Marketing as % of Revenue | C40: 0.55 | D40: 0.4 | E40: 0.3 | F40: 0.22 | G40: 0.18 | H40: Declining as organic grows
A41: Tax Rate | C41: 0.15 | D41: 0.15 | E41: 0.15 | F41: 0.15 | G41: 0.15 | H41: Simples Nacional / presumido
A42: Depreciation (% of PP&E) | C42: 0.2 | D42: 0.2 | E42: 0.2 | F42: 0.2 | G42: 0.2 | H42: 5-year straight line
A43: Capex (USD) | B43: 350000 | C43: 180000 | D43: 250000 | E43: 200000 | F43: 300000 | G43: 400000 | H43: Tech + office
A44: Initial Equity Investment | B44: 920000 | H44: Seed round

Sheet Revenue Detail
A1: AeroDesk — Revenue Build-Up (USD)
B2: Year 0 (Pre-Rev) | C2: Year 1 | D2: Year 2 | E2: Year 3 | F2: Year 4 | G2: Year 5 | H2: Notes / Source
A3: 1. DEALER SUBSCRIPTIONS
A4: Active Dealer Subscribers | B4: =Assumptions!B14 -> 0 | C4: =Assumptions!C14 -> 40 | D4: =Assumptions!D14 -> 150 | E4: =Assumptions!E14 -> 380 | F4: =Assumptions!F14 -> 650 | G4: =Assumptions!G14 -> 1000
A5: Avg Monthly Fee ($) | C5: =Assumptions!C21 -> 180 | D5: =Assumptions!D21 -> 220 | E5: =Assumptions!E21 -> 260 | F5: =Assumptions!F21 -> 300 | G5: =Assumptions!G21 -> 340
A6: Dealer Subscription Revenue | B6: 0 | C6: =C4*C5*12 -> 86400 | D6: =D4*D5*12 -> 396000 | E6: =E4*E5*12 -> 1185600 | F6: =F4*F5*12 -> 2340000 | G6: =G4*G5*12 -> 4080000
A8: 2. FEATURED LISTINGS
A9: Featured Listings Sold | B9: =Assumptions!B23 -> 0 | C9: =Assumptions!C23 -> 120 | D9: =Assumptions!D23 -> 450 | E9: =Assumptions!E23 -> 1100 | F9: =Assumptions!F23 -> 2000 | G9: =Assumptions!G23 -> 3500
A10: Avg Fee per Featured Listing | C10: =Assumptions!C22 -> 350 | D10: =Assumptions!D22 -> 400 | E10: =Assumptions!E22 -> 450 | F10: =Assumptions!F22 -> 500 | G10: =Assumptions!G22 -> 550
A11: Featured Listing Revenue | B11: 0 | C11: =C9*C10 -> 42000 | D11: =D9*D10 -> 180000 | E11: =E9*E10 -> 495000 | F11: =F9*F10 -> 1000000 | G11: =G9*G10 -> 1925000
A13: 3. INDIVIDUAL LISTINGS
A14: Individual Listings Sold | B14: =Assumptions!B25 -> 0 | C14: =Assumptions!C25 -> 200 | D14: =Assumptions!D25 -> 800 | E14: =Assumptions!E25 -> 2000 | F14: =Assumptions!F25 -> 4000 | G14: =Assumptions!G25 -> 7000
A15: Avg Fee per Listing | C15: =Assumptions!C24 -> 80 | D15: =Assumptions!D24 -> 90 | E15: =Assumptions!E24 -> 100 | F15: =Assumptions!F24 -> 110 | G15: =Assumptions!G24 -> 120
A16: Individual Listing Revenue | B16: 0 | C16: =C14*C15 -> 16000 | D16: =D14*D15 -> 72000 | E16: =E14*E15 -> 200000 | F16: =F14*F15 -> 440000 | G16: =G14*G15 -> 840000
A18: 4. TRANSACTION COMMISSIONS
A19: Transactions Facilitated | B19: =Assumptions!B18 -> 0 | C19: =Assumptions!C18 -> 15 | D19: =Assumptions!D18 -> 80 | E19: =Assumptions!E18 -> 250 | F19: =Assumptions!F18 -> 550 | G19: =Assumptions!G18 -> 1100
A20: Avg Listing Value | C20: =Assumptions!C17 -> 850000 | D20: =Assumptions!D17 -> 900000 | E20: =Assumptions!E17 -> 950000 | F20: =Assumptions!F17 -> 1000000 | G20: =Assumptions!G17 -> 1050000
A21: Commission Rate | C21: =Assumptions!C26 -> 0.005 | D21: =Assumptions!D26 -> 0.008 | E21: =Assumptions!E26 -> 0.01 | F21: =Assumptions!F26 -> 0.012 | G21: =Assumptions!G26 -> 0.015
A22: Transaction Commission Revenue | B22: 0 | C22: =C19*C20*C21 -> 63750 | D22: =D19*D20*D21 -> 576000 | E22: =E19*E20*E21 -> 2375000 | F22: =F19*F20*F21 -> 6600000 | G22: =G19*G20*G21 -> 17325000
A24: 5. ANCILLARY SERVICES (Insurance, PPI, Legal, Interior)
A25: Insurance Referral Revenue | B25: 0 | C25: =Assumptions!C27*Assumptions!C28 -> 5000 | D25: =Assumptions!D27*Assumptions!D28 -> 30000 | E25: =Assumptions!E27*Assumptions!E28 -> 126000 | F25: =Assumptions!F27*Assumptions!F28 -> 300000 | G25: =Assumptions!G27*Assumptions!G28 -> 640000
A26: Pre-Purchase Inspection Referral Revenue | B26: 0 | C26: =Assumptions!C29*Assumptions!C30 -> 8000 | D26: =Assumptions!D29*Assumptions!D30 -> 54000 | E26: =Assumptions!E29*Assumptions!E30 -> 200000 | F26: =Assumptions!F29*Assumptions!F30 -> 450000 | G26: =Assumptions!G29*Assumptions!G30 -> 900000
A27: Legal/Contract Support Referral Revenue | B27: 0 | C27: =Assumptions!C31*Assumptions!C32 -> 3200 | D27: =Assumptions!D31*Assumptions!D32 -> 22500 | E27: =Assumptions!E31*Assumptions!E32 -> 90000 | F27: =Assumptions!F31*Assumptions!F32 -> 227500 | G27: =Assumptions!G31*Assumptions!G32 -> 490000
A28: Total Ancillary Services Revenue | B28: 0 | C28: =SUM(C25:C27) -> 16200 | D28: =SUM(D25:D27) -> 106500 | E28: =SUM(E25:E27) -> 416000 | F28: =SUM(F25:F27) -> 977500 | G28: =SUM(G25:G27) -> 2030000
A30: 6. DATA & ANALYTICS
A31: Data Subscribers | B31: =Assumptions!B33 -> 0 | C31: =Assumptions!C33 -> 10 | D31: =Assumptions!D33 -> 40 | E31: =Assumptions!E33 -> 100 | F31: =Assumptions!F33 -> 200 | G31: =Assumptions!G33 -> 350
A32: Avg Monthly Fee | C32: =Assumptions!C34 -> 250 | D32: =Assumptions!D34 -> 300 | E32: =Assumptions!E34 -> 350 | F32: =Assumptions!F34 -> 400 | G32: =Assumptions!G34 -> 450
A33: Data & Analytics Revenue | B33: 0 | C33: =C31*C32*12 -> 30000 | D33: =D31*D32*12 -> 144000 | E33: =E31*E32*12 -> 420000 | F33: =F31*F32*12 -> 960000 | G33: =G31*G32*12 -> 1890000
A35: TOTAL REVENUE
A36: TOTAL REVENUE | B36: 0 | C36: =C6+C11+C16+C22+C28+C33 -> 254350 | D36: =D6+D11+D16+D22+D28+D33 -> 1474500 | E36: =E6+E11+E16+E22+E28+E33 -> 5091600 | F36: =F6+F11+F16+F22+F28+F33 -> 12317500 | G36: =G6+G11+G16+G22+G28+G33 -> 28090000
A38: Revenue Mix (%)
A39: Dealer Subscriptions % | C39: =IF(C36=0,0,C6/C36) -> 0.3396894 | D39: =IF(D36=0,0,D6/D36) -> 0.26856562 | E39: =IF(E36=0,0,E6/E36) -> 0.23285411 | F39: =IF(F36=0,0,F6/F36) -> 0.18997361 | G39: =IF(G36=0,0,G6/G36) -> 0.14524742
A40: Featured Listings % | C40: =IF(C36=0,0,C11/C36) -> 0.16512679 | D40: =IF(D36=0,0,D11/D36) -> 0.12207528 | E40: =IF(E36=0,0,E11/E36) -> 0.097218949 | F40: =IF(F36=0,0,F11/F36) -> 0.081185305 | G40: =IF(G36=0,0,G11/G36) -> 0.068529726
A41: Individual Listings % | C41: =IF(C36=0,0,C16/C36) -> 0.062905445 | D41: =IF(D36=0,0,D16/D36) -> 0.048830112 | E41: =IF(E36=0,0,E16/E36) -> 0.039280383 | F41: =IF(F36=0,0,F16/F36) -> 0.035721534 | G41: =IF(G36=0,0,G16/G36) -> 0.02990388
A42: Transaction Commissions % | C42: =IF(C36=0,0,C22/C36) -> 0.25063888 | D42: =IF(D36=0,0,D22/D36) -> 0.3906409 | E42: =IF(E36=0,0,E22/E36) -> 0.46645455 | F42: =IF(F36=0,0,F22/F36) -> 0.53582302 | G42: =IF(G36=0,0,G22/G36) -> 0.61676753
A43: Ancillary Services % | C43: =IF(C36=0,0,C28/C36) -> 0.063691763 | D43: =IF(D36=0,0,D28/D36) -> 0.072227874 | E43: =IF(E36=0,0,E28/E36) -> 0.081703197 | F43: =IF(F36=0,0,F28/F36) -> 0.079358636 | G43: =IF(G36=0,0,G28/G36) -> 0.072267711
A44: Data & Analytics % | C44: =IF(C36=0,0,C33/C36) -> 0.11794771 | D44: =IF(D36=0,0,D33/D36) -> 0.097660224 | E44: =IF(E36=0,0,E33/E36) -> 0.082488805 | F44: =IF(F36=0,0,F33/F36) -> 0.077937893 | G44: =IF(G36=0,0,G33/G36) -> 0.067283731

Sheet Income Statement
A1: AeroDesk — Income Statement (USD)
B2: Year 0 (Pre-Rev) | C2: Year 1 | D2: Year 2 | E2: Year 3 | F2: Year 4 | G2: Year 5 | H2: Notes / Source
A3: REVENUE
A4: Total Revenue | B4: ='Revenue Detail'!B36 -> 0 | C4: ='Revenue Detail'!C36 -> 254350 | D4: ='Revenue Detail'!D36 -> 1474500 | E4: ='Revenue Detail'!E36 -> 5091600 | F4: ='Revenue Detail'!F36 -> 12317500 | G4: ='Revenue Detail'!G36 -> 28090000
A6: COST OF GOODS SOLD (COGS)
A7: Payment Processing (2.5% of Revenue) | B7: 0 | C7: =C4*0.025 -> 6358.75 | D7: =D4*0.025 -> 36862.5 | E7: =E4*0.025 -> 127290 | F7: =F4*0.025 -> 307937.5 | G7: =G4*0.025 -> 702250
A8: Cloud Infrastructure & Hosting | B8: =Assumptions!B39*12 -> 6000 | C8: =Assumptions!C39*12 -> 24000 | D8: =Assumptions!D39*12 -> 54000 | E8: =Assumptions!E39*12 -> 96000 | F8: =Assumptions!F39*12 -> 168000 | G8: =Assumptions!G39*12 -> 264000
A9: Data Licensing & 3rd Party APIs | B9: 0 | C9: 12000 | D9: 24000 | E9: 36000 | F9: 48000 | G9: 60000
A10: Customer Support (Outsourced) | B10: 0 | C10: 24000 | D10: 48000 | E10: 84000 | F10: 144000 | G10: 240000
A11: Total COGS | B11: =SUM(B7:B10) -> 6000 | C11: =SUM(C7:C10) -> 66358.75 | D11: =SUM(D7:D10) -> 162862.5 | E11: =SUM(E7:E10) -> 343290 | F11: =SUM(F7:F10) -> 667937.5 | G11: =SUM(G7:G10) -> 1266250
A12: Gross Profit | B12: =B4-B11 -> -6000 | C12: =C4-C11 -> 187991.25 | D12: =D4-D11 -> 1311637.5 | E12: =E4-E11 -> 4748310 | F12: =F4-F11 -> 11649562 | G12: =G4-G11 -> 26823750
A13: Gross Margin % | C13: =IF(C4=0,0,C12/C4) -> 0.73910458 | D13: =IF(D4=0,0,D12/D4) -> 0.8895473 | E13: =IF(E4=0,0,E12/E4) -> 0.93257719 | F13: =IF(F4=0,0,F12/F4) -> 0.94577329 | G13: =IF(G4=0,0,G12/G4) -> 0.95492168
A15: SG&A EXPENSES
A16: Salaries & Benefits | B16: =Assumptions!B37*Assumptions!B38 -> 0 | C16: =Assumptions!C37*Assumptions!C38 -> 480000 | D16: =Assumptions!D37*Assumptions!D38 -> 910000 | E16: =Assumptions!E37*Assumptions!E38 -> 1540000 | F16: =Assumptions!F37*Assumptions!F38 -> 2400000 | G16: =Assumptions!G37*Assumptions!G38 -> 3600000
A17: Marketing & Customer Acquisition | B17: 30000 | C17: =MAX(C4*Assumptions!C40,60000) -> 139892.5 | D17: =MAX(D4*Assumptions!D40,60000) -> 589800 | E17: =MAX(E4*Assumptions!E40,60000) -> 1527480 | F17: =MAX(F4*Assumptions!F40,60000) -> 2709850 | G17: =MAX(G4*Assumptions!G40,60000) -> 5056200
A18: Office & Co-working | B18: 6000 | C18: 24000 | D18: 36000 | E18: 60000 | F18: 96000 | G18: 144000
A19: Professional Services (Legal, Accounting) | B19: 15000 | C19: 30000 | D19: 48000 | E19: 72000 | F19: 96000 | G19: 120000
A20: Software & Tools (SaaS) | B20: 3000 | C20: 18000 | D20: 30000 | E20: 48000 | F20: 72000 | G20: 96000
A21: Travel & Events (LABACE, conferences) | B21: 5000 | C21: 30000 | D21: 48000 | E21: 72000 | F21: 96000 | G21: 120000
A22: D&O Insurance | B22: 0 | C22: 12000 | D22: 18000 | E22: 24000 | F22: 36000 | G22: 48000
A23: Total SG&A | B23: =SUM(B16:B22) -> 59000 | C23: =SUM(C16:C22) -> 733892.5 | D23: =SUM(D16:D22) -> 1679800 | E23: =SUM(E16:E22) -> 3343480 | F23: =SUM(F16:F22) -> 5505850 | G23: =SUM(G16:G22) -> 9184200
A25: EBITDA | B25: =B12-B23 -> -65000 | C25: =C12-C23 -> -545901.25 | D25: =D12-D23 -> -368162.5 | E25: =E12-E23 -> 1404830 | F25: =F12-F23 -> 6143712.5 | G25: =G12-G23 -> 17639550
A26: EBITDA Margin % | C26: =IF(C4=0,0,C25/C4) -> -2.1462601 | D26: =IF(D4=0,0,D25/D4) -> -0.24968633 | E26: =IF(E4=0,0,E25/E4) -> 0.2759113 | F26: =IF(F4=0,0,F25/F4) -> 0.49877918 | G26: =IF(G4=0,0,G25/G4) -> 0.62796547
A28: Depreciation & Amortization | B28: =Assumptions!B43*Assumptions!B42 -> 0 | C28: =Assumptions!C43*Assumptions!C42 -> 36000 | D28: =Assumptions!D43*Assumptions!D42 -> 50000 | E28: =Assumptions!E43*Assumptions!E42 -> 40000 | F28: =Assumptions!F43*Assumptions!F42 -> 60000 | G28: =Assumptions!G43*Assumptions!G42 -> 80000
A29: EBIT | B29: =B25-B28 -> -65000 | C29: =C25-C28 -> -581901.25 | D29: =D25-D28 -> -418162.5 | E29: =E25-E28 -> 1364830 | F29: =F25-F28 -> 6083712.5 | G29: =G25-G28 -> 17559550
A30: Interest Expense | B30: 0 | C30: 0 | D30: 0 | E30: 0 | F30: 0 | G30: 0
A31: EBT (Earnings Before Tax) | B31: =B29-B30 -> -65000 | C31: =C29-C30 -> -581901.25 | D31: =D29-D30 -> -418162.5 | E31: =E29-E30 -> 1364830 | F31: =F29-F30 -> 6083712.5 | G31: =G29-G30 -> 17559550
A32: Income Tax | B32: 0 | C32: =IF(C31>0,C31*Assumptions!C41,0) -> 0 | D32: =IF(D31>0,D31*Assumptions!D41,0) -> 0 | E32: =IF(E31>0,E31*Assumptions!E41,0) -> 204724.5 | F32: =IF(F31>0,F31*Assumptions!F41,0) -> 912556.88 | G32: =IF(G31>0,G31*Assumptions!G41,0) -> 2633932.5
A33: NET INCOME | B33: =B31-B32 -> -65000 | C33: =C31-C32 -> -581901.25 | D33: =D31-D32 -> -418162.5 | E33: =E31-E32 -> 1160105.5 | F33: =F31-F32 -> 5171155.6 | G33: =G31-G32 -> 14925618
A34: Net Margin % | C34: =IF(C4=0,0,C33/C4) -> -2.2877973 | D34: =IF(D4=0,0,D33/D4) -> -0.28359613 | E34: =IF(E4=0,0,E33/E4) -> 0.22784694 | F34: =IF(F4=0,0,F33/F4) -> 0.41982185 | G34: =IF(G4=0,0,G33/G4) -> 0.53134986

Sheet Balance Sheet
A1: AeroDesk — Balance Sheet (USD)
B2: Year 0 (Pre-Rev) | C2: Year 1 | D2: Year 2 | E2: Year 3 | F2: Year 4 | G2: Year 5 | H2: Notes / Source
A3: ASSETS
A4: Cash & Cash Equivalents | B4: 920000 | C4: =B4+'Income Statement'!C33+'Income Statement'!C28-Assumptions!C43 -> 194098.75 | D4: =C4+'Income Statement'!D33+'Income Statement'!D28-Assumptions!D43 -> -424063.75 | E4: =D4+'Income Statement'!E33+'Income Statement'!E28-Assumptions!E43 -> 576041.75 | F4: =E4+'Income Statement'!F33+'Income Statement'!F28-Assumptions!F43 -> 5507197.4 | G4: =F4+'Income Statement'!G33+'Income Statement'!G28-Assumptions!G43 -> 20112815
A5: Accounts Receivable | B5: 0 | C5: ='Income Statement'!C4/12*2 -> 42391.667 | D5: ='Income Statement'!D4/12*2 -> 245750 | E5: ='Income Statement'!E4/12*2 -> 848600 | F5: ='Income Statement'!F4/12*2 -> 2052916.7 | G5: ='Income Statement'!G4/12*2 -> 4681666.7
A6: Prepaid Expenses | B6: 10000 | C6: 20000 | D6: 30000 | E6: 40000 | F6: 50000 | G6: 60000
A7: Total Current Assets | B7: =SUM(B4:B6) -> 930000 | C7: =SUM(C4:C6) -> 256490.42 | D7: =SUM(D4:D6) -> -148313.75 | E7: =SUM(E4:E6) -> 1464641.8 | F7: =SUM(F4:F6) -> 7610114 | G7: =SUM(G4:G6) -> 24854482
A9: PP&E (Net) | B9: =Assumptions!B43 -> 350000 | C9: =B9+Assumptions!C43-'Income Statement'!C28 -> 494000 | D9: =C9+Assumptions!D43-'Income Statement'!D28 -> 694000 | E9: =D9+Assumptions!E43-'Income Statement'!E28 -> 854000 | F9: =E9+Assumptions!F43-'Income Statement'!F28 -> 1094000 | G9: =F9+Assumptions!G43-'Income Statement'!G28 -> 1414000
A10: TOTAL ASSETS | B10: =B7+B9 -> 1280000 | C10: =C7+C9 -> 750490.42 | D10: =D7+D9 -> 545686.25 | E10: =E7+E9 -> 2318641.8 | F10: =F7+F9 -> 8704114 | G10: =G7+G9 -> 26268482
A12: LIABILITIES
A13: Accounts Payable | B13: 15000 | C13: ='Income Statement'!C11/12*1.5 -> 8294.8438 | D13: ='Income Statement'!D11/12*1.5 -> 20357.812 | E13: ='Income Statement'!E11/12*1.5 -> 42911.25 | F13: ='Income Statement'!F11/12*1.5 -> 83492.188 | G13: ='Income Statement'!G11/12*1.5 -> 158281.25
A14: Deferred Revenue | B14: 0 | C14: 15000 | D14: 40000 | E14: 80000 | F14: 130000 | G14: 200000
A15: Accrued Expenses | B15: 5000 | C15: 20000 | D15: 35000 | E15: 55000 | F15: 80000 | G15: 110000
A16: Total Liabilities | B16: =SUM(B13:B15) -> 20000 | C16: =SUM(C13:C15) -> 43294.844 | D16: =SUM(D13:D15) -> 95357.812 | E16: =SUM(E13:E15) -> 177911.25 | F16: =SUM(F13:F15) -> 293492.19 | G16: =SUM(G13:G15) -> 468281.25
A18: EQUITY
A19: Paid-in Capital | B19: 920000 | C19: 920000 | D19: 920000 | E19: 920000 | F19: 920000 | G19: 920000
A20: Retained Earnings | B20: 0 | C20: =B20+'Income Statement'!C33 -> -581901.25 | D20: =C20+'Income Statement'!D33 -> -1000063.8 | E20: =D20+'Income Statement'!E33 -> 160041.75 | F20: =E20+'Income Statement'!F33 -> 5331197.4 | G20: =F20+'Income Statement'!G33 -> 20256815
A21: Total Equity | B21: =B19+B20 -> 920000 | C21: =C19+C20 -> 338098.75 | D21: =D19+D20 -> -80063.75 | E21: =E19+E20 -> 1080041.8 | F21: =F19+F20 -> 6251197.4 | G21: =G19+G20 -> 21176815
A23: TOTAL LIABILITIES + EQUITY | B23: =B16+B21 -> 940000 | C23: =C16+C21 -> 381393.59 | D23: =D16+D21 -> 15294.062 | E23: =E16+E21 -> 1257953 | F23: =F16+F21 -> 6544689.6 | G23: =G16+G21 -> 21645096
A25: Balance Check (Assets - L&E) | B25: =B10-B23 -> 340000 | C25: =C10-C23 -> 369096.82 | D25: =D10-D23 -> 530392.19 | E25: =E10-E23 -> 1060688.8 | F25: =F10-F23 -> 2159424.5 | G25: =G10-G23 -> 4623385.4

Sheet Cash Flow
A1: AeroDesk — Cash Flow Statement (USD)
B2: Year 0 (Pre-Rev) | C2: Year 1 | D2: Year 2 | E2: Year 3 | F2: Year 4 | G2: Year 5 | H2: Notes / Source
A3: CASH FLOW FROM OPERATIONS
A4: Net Income | B4: ='Income Statement'!B33 -> -65000 | C4: ='Income Statement'!C33 -> -581901.25 | D4: ='Income Statement'!D33 -> -418162.5 | E4: ='Income Statement'!E33 -> 1160105.5 | F4: ='Income Statement'!F33 -> 5171155.6 | G4: ='Income Statement'!G33 -> 14925618
A5: (+) Depreciation & Amortization | B5: ='Income Statement'!B28 -> 0 | C5: ='Income Statement'!C28 -> 36000 | D5: ='Income Statement'!D28 -> 50000 | E5: ='Income Statement'!E28 -> 40000 | F5: ='Income Statement'!F28 -> 60000 | G5: ='Income Statement'!G28 -> 80000
A6: Changes in Working Capital | B6: -30000 | C6: =-('Balance Sheet'!C5-'Balance Sheet'!B5)+('Balance Sheet'!C13-'Balance Sheet'!B13)+('Balance Sheet'!C14-'Balance Sheet'!B14)+('Balance Sheet'!C15-'Balance Sheet'!B15)-('Balance Sheet'!C6-'Balance Sheet'!B6) -> -29096.823 | D6: =-('Balance Sheet'!D5-'Balance Sheet'!C5)+('Balance Sheet'!D13-'Balance Sheet'!C13)+('Balance Sheet'!D14-'Balance Sheet'!C14)+('Balance Sheet'!D15-'Balance Sheet'!C15)-('Balance Sheet'!D6-'Balance Sheet'!C6) -> -161295.36 | E6: =-('Balance Sheet'!E5-'Balance Sheet'!D5)+('Balance Sheet'!E13-'Balance Sheet'!D13)+('Balance Sheet'!E14-'Balance Sheet'!D14)+('Balance Sheet'!E15-'Balance Sheet'!D15)-('Balance Sheet'!E6-'Balance Sheet'!D6) -> -530296.56 | F6: =-('Balance Sheet'!F5-'Balance Sheet'!E5)+('Balance Sheet'!F13-'Balance Sheet'!E13)+('Balance Sheet'!F14-'Balance Sheet'!E14)+('Balance Sheet'!F15-'Balance Sheet'!E15)-('Balance Sheet'!F6-'Balance Sheet'!E6) -> -1098735.7 | G6: =-('Balance Sheet'!G5-'Balance Sheet'!F5)+('Balance Sheet'!G13-'Balance Sheet'!F13)+('Balance Sheet'!G14-'Balance Sheet'!F14)+('Balance Sheet'!G15-'Balance Sheet'!F15)-('Balance Sheet'!G6-'Balance Sheet'!F6) -> -2463960.9
A7: Net Cash from Operations | B7: =SUM(B4:B6) -> -95000 | C7: =SUM(C4:C6) -> -574998.07 | D7: =SUM(D4:D6) -> -529457.86 | E7: =SUM(E4:E6) -> 669808.94 | F7: =SUM(F4:F6) -> 4132419.9 | G7: =SUM(G4:G6) -> 12541657
A9: CASH FLOW FROM INVESTING
A10: Capital Expenditures | B10: =-Assumptions!B43 -> -350000 | C10: =-Assumptions!C43 -> -180000 | D10: =-Assumptions!D43 -> -250000 | E10: =-Assumptions!E43 -> -200000 | F10: =-Assumptions!F43 -> -300000 | G10: =-Assumptions!G43 -> -400000
A11: Net Cash from Investing | B11: =B10 -> -350000 | C11: =C10 -> -180000 | D11: =D10 -> -250000 | E11: =E10 -> -200000 | F11: =F10 -> -300000 | G11: =G10 -> -400000
A13: CASH FLOW FROM FINANCING
A14: Equity Investment | B14: 920000 | C14: 0 | D14: 0 | E14: 0 | F14: 0 | G14: 0
A15: Net Cash from Financing | B15: =B14 -> 920000 | C15: =C14 -> 0 | D15: =D14 -> 0 | E15: =E14 -> 0 | F15: =F14 -> 0 | G15: =G14 -> 0
A17: NET CHANGE IN CASH | B17: =B7+B11+B15 -> 475000 | C17: =C7+C11+C15 -> -754998.07 | D17: =D7+D11+D15 -> -779457.86 | E17: =E7+E11+E15 -> 469808.94 | F17: =F7+F11+F15 -> 3832419.9 | G17: =G7+G11+G15 -> 12141657
A19: Beginning Cash | B19: 0 | C19: =B20 -> 475000 | D19: =C20 -> -279998.07 | E19: =D20 -> -1059455.9 | F19: =E20 -> -589647 | G19: =F20 -> 3242772.9
A20: Ending Cash | B20: =B19+B17 -> 475000 | C20: =C19+C17 -> -279998.07 | D20: =D19+D17 -> -1059455.9 | E20: =E19+E17 -> -589647 | F20: =F19+F17 -> 3242772.9 | G20: =G19+G17 -> 15384429

Sheet IRR & Returns
A1: AeroDesk — IRR & Return Analysis
B2: Year 0 (Pre-Rev) | C2: Year 1 | D2: Year 2 | E2: Year 3 | F2: Year 4 | G2: Year 5 | H2: Notes / Source
A3: FREE CASH FLOW TO EQUITY
A4: Net Cash from Operations | B4: ='Cash Flow'!B7 -> -95000 | C4: ='Cash Flow'!C7 -> -574998.07 | D4: ='Cash Flow'!D7 -> -529457.86 | E4: ='Cash Flow'!E7 -> 669808.94 | F4: ='Cash Flow'!F7 -> 4132419.9 | G4: ='Cash Flow'!G7 -> 12541657
A5: Capital Expenditures | B5: ='Cash Flow'!B10 -> -350000 | C5: ='Cash Flow'!C10 -> -180000 | D5: ='Cash Flow'!D10 -> -250000 | E5: ='Cash Flow'!E10 -> -200000 | F5: ='Cash Flow'!F10 -> -300000 | G5: ='Cash Flow'!G10 -> -400000
A6: Free Cash Flow (FCFE) | B6: =B4+B5 -> -445000 | C6: =C4+C5 -> -754998.07 | D6: =D4+D5 -> -779457.86 | E6: =E4+E5 -> 469808.94 | F6: =F4+F5 -> 3832419.9 | G6: =G4+G5 -> 12141657
A8: INVESTOR RETURN ANALYSIS
A9: Initial Investment (outflow) | B9: =-Assumptions!B44 -> -920000 | C9: 0 | D9: 0 | E9: 0 | F9: 0 | G9: 0
A10: Cash Flows (FCFE) | B10: =B6 -> -445000 | C10: =C6 -> -754998.07 | D10: =D6 -> -779457.86 | E10: =E6 -> 469808.94 | F10: =F6 -> 3832419.9 | G10: =G6 -> 12141657
A11: Terminal Value (10x Y5 EBITDA) | G11: ='Income Statement'!G25*$B$16 -> 176395500
A12: Total Cash Flow to Investor | B12: =B9 -> -920000 | C12: =C10 -> -754998.07 | D12: =D10 -> -779457.86 | E12: =E10 -> 469808.94 | F12: =F10 -> 3832419.9 | G12: =G10+G11 -> 1.8853716e+08
A14: IRR (Internal Rate of Return) | B14: =IRR(B12:G12) -> 1.7456725
A16: Exit Multiple Applied | B16: 10
A17: Terminal Value / Investment Multiple | B17: =G11/(-B9) -> 191.73424
A19: MARKET SHARE EVOLUTION
A20: Online Aircraft Marketplace TAM (USD M) | C20: =Assumptions!C8 -> 800 | D20: =Assumptions!D8 -> 920 | E20: =Assumptions!E8 -> 1058 | F20: =Assumptions!F8 -> 1217 | G20: =Assumptions!G8 -> 1400
A21: AeroDesk Revenue (USD M) | C21: ='Revenue Detail'!C36/1000000 -> 0.25435 | D21: ='Revenue Detail'!D36/1000000 -> 1.4745 | E21: ='Revenue Detail'!E36/1000000 -> 5.0916 | F21: ='Revenue Detail'!F36/1000000 -> 12.3175 | G21: ='Revenue Detail'!G36/1000000 -> 28.09
A22: Market Share of Online TAM | C22: =IF(C20=0,0,C21/C20) -> 0.0003179375 | D22: =IF(D20=0,0,D21/D20) -> 0.0016027174 | E22: =IF(E20=0,0,E21/E20) -> 0.0048124764 | F22: =IF(F20=0,0,F21/F20) -> 0.0101212 | G22: =IF(G20=0,0,G21/G20) -> 0.020064286
A24: Controller.com Est. Revenue (USD M) | C24: 18.2 | D24: 19 | E24: 19.5 | F24: 20 | G24: 20.5
A25: AeroDesk as % of Controller Revenue | C25: =IF(C24=0,0,C21/C24) -> 0.013975275 | D25: =IF(D24=0,0,D21/D24) -> 0.077605263 | E25: =IF(E24=0,0,E21/E24) -> 0.26110769 | F25: =IF(F24=0,0,F21/F24) -> 0.615875 | G25: =IF(G24=0,0,G21/G24) -> 1.3702439
